dependente/__init__.py
dependente/_version.py
dependente/cli.py
dependente/converters.py
dependente/parsers.py
dependente/tests/__init__.py
dependente/tests/conftest.py
dependente/tests/test_cli_utils.py
dependente/tests/test_converters.py
dependente/tests/test_parsers.py
dependente/tests/data/sample_pyproject.toml
dependente/tests/data/sample_setup.cfg
dependente-0.3.0.dist-info/LICENSE.txt
dependente-0.3.0.dist-info/METADATA
dependente-0.3.0.dist-info/WHEEL
dependente-0.3.0.dist-info/entry_points.txt
dependente-0.3.0.dist-info/top_level.txt
dependente-0.3.0.dist-info/zip-safe
dependente-0.3.0.dist-info/RECORD
