Metadata-Version: 2.1
Name: dependente
Version: 0.3.0
Summary: Inspect Python package dependencies
Home-page: https://github.com/fatiando/dependente
Author: The Dependente Developers
Author-email: fatiandoaterra@protonmail.com
Maintainer: "Leonardo Uieda"
Maintainer-email: leouieda@gmail.com
License: MIT
Project-URL: Release Notes, https://github.com/fatiando/dependente/releases
Project-URL: Bug Tracker, https://github.com/fatiando/dependente/issues
Project-URL: Source Code, https://github.com/fatiando/dependente
Keywords: dependencies,pyproject,setuptools
Platform: any
Classifier: Development Status :: 3 - Alpha
Classifier: Environment :: Console
Classifier: Intended Audience :: Developers
Classifier: License :: OSI Approved :: MIT License
Classifier: Natural Language :: English
Classifier: Operating System :: OS Independent
Classifier: Topic :: Software Development :: Libraries
Classifier: Programming Language :: Python :: 3 :: Only
Classifier: Programming Language :: Python :: 3.6
Classifier: Programming Language :: Python :: 3.7
Classifier: Programming Language :: Python :: 3.8
Classifier: Programming Language :: Python :: 3.9
Classifier: Programming Language :: Python :: 3.10
Requires-Python: >=3.6
License-File: LICENSE.txt
Requires-Dist: click <9.0.0,>=8.0.0
Requires-Dist: tomli <3.0.0,>=1.1.0
